structuredscraper/__init__.py
structuredscraper/scraper.py
structuredscraper/utils.py
structuredscraper/tests/__init__.py
structuredscraper/tests/scraper_tests.py
structuredscraper-0.1.0.dist-info/LICENSE
structuredscraper-0.1.0.dist-info/METADATA
structuredscraper-0.1.0.dist-info/WHEEL
structuredscraper-0.1.0.dist-info/top_level.txt
structuredscraper-0.1.0.dist-info/RECORD
