Metadata-Version: 2.2
Name: structuredscraper
Version: 0.1.0
Summary: A structured example-driven automatic web scraper.
Author-email: ExplodingFreeze <19326774+ExplodingFreeze@users.noreply.github.com>
License: MIT License
Project-URL: Homepage, https://github.com/ExplodingFreeze/structuredscraper
Keywords: scraper
Classifier: License :: OSI Approved :: MIT License
Classifier: Programming Language :: Python
Classifier: Programming Language :: Python :: 3
Requires-Python: >=3.6
License-File: LICENSE
Requires-Dist: lxml
Provides-Extra: dev
Requires-Dist: black; extra == "dev"
Requires-Dist: bumpver; extra == "dev"
Requires-Dist: isort; extra == "dev"
Requires-Dist: pip-tools; extra == "dev"
Requires-Dist: pytest; extra == "dev"
